LICENSE
README.md
streamlit_sal/__init__.py
streamlit_sal/components.py
streamlit_sal/sal_config.py
streamlit_sal/sass/__init__.py
streamlit_sal/sass/_layout.scss
streamlit_sal/sass/_streamlit-component-map.scss
streamlit_sal/sass/_style-builder.scss
streamlit_sal/sass/_utilities.scss
streamlit_sal/scripts/__init__.py
streamlit_sal/scripts/cli.py
streamlit_sal/scripts/init_files.py
streamlit_sal/templates/.streamlit_sal
streamlit_sal/templates/__init__.py
streamlit_sal/templates/main.scss
streamlit_sal/utils/__init__.py
streamlit_sal/utils/compile.py
streamlit_sal/utils/config.py
streamlit_sal/utils/stylesheet.py
streamlit_sal-0.2.0.dist-info/LICENSE
streamlit_sal-0.2.0.dist-info/METADATA
streamlit_sal-0.2.0.dist-info/WHEEL
streamlit_sal-0.2.0.dist-info/entry_points.txt
streamlit_sal-0.2.0.dist-info/RECORD
