Metadata-Version: 2.1
Name: streamlit-sal
Version: 0.2.0
Summary: Style and layout for your Streamlit app using SASS
Home-page: https://github.com/datarobot-oss/streamlit-sal
License: MIT
Author: DataRobot Applications Team
Author-email: apps-oss@datarobot.com
Requires-Python: >=3.8, !=2.7.*, !=3.0.*, !=3.1.*, !=3.2.*, !=3.3.*, !=3.4.*, !=3.5.*, !=3.6.*, !=3.7.*
Classifier: License :: OSI Approved :: MIT License
Classifier: Programming Language :: Python :: 3
Classifier: Programming Language :: Python :: 3.8
Classifier: Programming Language :: Python :: 3.9
Classifier: Programming Language :: Python :: 3.10
Classifier: Programming Language :: Python :: 3.11
Classifier: Programming Language :: Python :: 3.12
Requires-Dist: click (>=8.1.7,<9.0.0)
Requires-Dist: libsass (>=0.23.0,<0.24.0)
Requires-Dist: streamlit (>=1.41.0)
Project-URL: Documentation, https://github.com/datarobot-oss/streamlit-sal
Project-URL: Repository, https://github.com/datarobot-oss/streamlit-sal
